tinote/__init__.py
tinote/main.py
tinote/update.py
tinote-1.2.1.dist-info/LICENSE
tinote-1.2.1.dist-info/METADATA
tinote-1.2.1.dist-info/WHEEL
tinote-1.2.1.dist-info/entry_points.txt
tinote-1.2.1.dist-info/top_level.txt
tinote-1.2.1.dist-info/RECORD
