Metadata-Version: 2.1
Name: tinote
Version: 1.2.1
Summary: A command-line note-taking tool
Home-page: https://github.com/aPeter1/tinote
Author: Alec Petersen
Author-email: k.alecpetersen@gmail.com
Classifier: Development Status :: 5 - Production/Stable
Classifier: Intended Audience :: Developers
Classifier: License :: OSI Approved :: MIT License
Classifier: Programming Language :: Python :: 3
Classifier: Programming Language :: Python :: 3.6
Classifier: Programming Language :: Python :: 3.7
Classifier: Programming Language :: Python :: 3.8
Classifier: Programming Language :: Python :: 3.9
Classifier: Programming Language :: Python :: 3.10
Classifier: Programming Language :: Python :: 3.11
Classifier: Topic :: Terminals
Requires-Python: >=3.6
License-File: LICENSE
